{"cameraMode":{"drawMode":0,"name":"Shaded","section":"Shading Mode"},"sceneLighting":true,"audioPlay":false,"sceneViewState":{"m_AlwaysRefresh":false,"showFog":true,"showSkybox":true,"showFlares":true,"showImageEffects":true,"showParticleSystems":true,"showVisualEffectGraphs":true,"m_FxEnabled":true},"in2DMode":false,"pivot":{"x":554.6425170898438,"y":154.63050842285157,"z":-2.005584716796875},"rotation":{"x":0.023687919601798059,"y":-0.000903080275747925,"z":-0.000021358522644732147,"w":-0.9997204542160034},"size":213.06410217285157,"orthographic":false}